{ "compressionlevel":-1,
 "height":18,
 "infinite":false,
 "layers":[
        {
         "id":2,
         "image":"D:\/Easter-Egg-project\/rpg-game\/static\/assets\/tomb0.png",
         "imageheight":575,
         "imagewidth":871,
         "name":"Background",
         "opacity":1,
         "type":"imagelayer",
         "visible":true,
         "x":0,
         "y":0
        }, 
        {
         "draworder":"topdown",
         "id":3,
         "name":"collider",
         "objects":[
                {
                 "height":93.3333333333333,
                 "id":15,
                 "name":"",
                 "rotation":0,
                 "type":"",
                 "visible":true,
                 "width":72.6666666666667,
                 "x":399.333333333333,
                 "y":232.666666666667
                }, 
                {
                 "height":134,
                 "id":19,
                 "name":"",
                 "rotation":0,
                 "type":"",
                 "visible":true,
                 "width":84,
                 "x":0,
                 "y":441.333333333333
                }, 
                {
                 "height":62.6666666666666,
                 "id":20,
                 "name":"",
                 "rotation":0,
                 "type":"",
                 "visible":true,
                 "width":786.666666666667,
                 "x":84,
                 "y":512.666666666667
                }, 
                {
                 "height":53.3333333333334,
                 "id":21,
                 "name":"",
                 "rotation":0,
                 "type":"",
                 "visible":true,
                 "width":175.333333333333,
                 "x":347.333333333333,
                 "y":458.666666666667
                }, 
                {
                 "height":511.333333333333,
                 "id":22,
                 "name":"",
                 "rotation":0,
                 "type":"",
                 "visible":true,
                 "width":22,
                 "x":848,
                 "y":0.666666666666667
                }, 
                {
                 "height":25.3333333333333,
                 "id":23,
                 "name":"",
                 "rotation":0,
                 "type":"",
                 "visible":true,
                 "width":35.3333333333334,
                 "x":757.333333333333,
                 "y":72
                }, 
                {
                 "height":199.333333333333,
                 "id":24,
                 "name":"",
                 "rotation":0,
                 "type":"",
                 "visible":true,
                 "width":44,
                 "x":803.333333333333,
                 "y":16.6666666666667
                }, 
                {
                 "height":70.6666666666667,
                 "id":25,
                 "name":"",
                 "rotation":0,
                 "type":"",
                 "visible":true,
                 "width":47.3333333333334,
                 "x":799.333333333333,
                 "y":255.333333333333
                }, 
                {
                 "height":71.3333333333333,
                 "id":26,
                 "name":"",
                 "rotation":0,
                 "type":"",
                 "visible":true,
                 "width":846.666666666667,
                 "x":0.666666666666629,
                 "y":0.666666666666671
                }, 
                {
                 "height":23.3333333333333,
                 "id":27,
                 "name":"",
                 "rotation":0,
                 "type":"",
                 "visible":true,
                 "width":32,
                 "x":85.3333333333333,
                 "y":72
                }, 
                {
                 "height":139.333333333333,
                 "id":28,
                 "name":"",
                 "rotation":0,
                 "type":"",
                 "visible":true,
                 "width":70,
                 "x":-0.666666666666667,
                 "y":71.3333333333333
                }, 
                {
                 "height":230.666666666667,
                 "id":29,
                 "name":"",
                 "rotation":0,
                 "type":"",
                 "visible":true,
                 "width":23.3333333333333,
                 "x":-0.666666666666667,
                 "y":209.333333333333
                }, 
                {
                 "height":64.6666666666667,
                 "id":30,
                 "name":"",
                 "rotation":0,
                 "type":"",
                 "visible":true,
                 "width":44.6666666666667,
                 "x":24.6666666666667,
                 "y":257.333333333333
                }, 
                {
                 "ellipse":true,
                 "height":38,
                 "id":31,
                 "name":"",
                 "rotation":0,
                 "type":"",
                 "visible":true,
                 "width":68.0000000000001,
                 "x":401.333333333333,
                 "y":213.333333333333
                }],
         "opacity":1,
         "type":"objectgroup",
         "visible":true,
         "x":0,
         "y":0
        }],
 "nextlayerid":4,
 "nextobjectid":33,
 "orientation":"orthogonal",
 "renderorder":"right-down",
 "tiledversion":"1.11.2",
 "tileheight":32,
 "tilesets":[],
 "tilewidth":32,
 "type":"map",
 "version":"1.10",
 "width":28
}